check50_junit/__init__.py
check50_junit/junit5.py
check50_junit/lib/junit-platform-console-standalone-1.6.2.jar
check50_junit-0.5.dist-info/LICENSE
check50_junit-0.5.dist-info/METADATA
check50_junit-0.5.dist-info/WHEEL
check50_junit-0.5.dist-info/top_level.txt
check50_junit-0.5.dist-info/RECORD
