Metadata-Version: 2.1
Name: check50-junit
Version: 0.5
Summary: A check50 extension for running and interpreting junit5 unit tests
Home-page: https://github.com/pazz/check50_junit
Author: Patrick Totzke
Author-email: patricktotzke@gmail.com
License: UNKNOWN
Platform: UNKNOWN
Classifier: Programming Language :: Python :: 3
Classifier: License :: OSI Approved :: MIT License
Classifier: Operating System :: OS Independent
Requires-Python: >=3.6
Requires-Dist: check50
Requires-Dist: check50-java
